Metadata-Version: 2.1
Name: backup-folder-to-zip
Version: 1.0.2
Summary: Copies an entire folder and its contains into a zip file whose filename increments.
Home-page: UNKNOWN
Author: Dari Developer
Author-email: hernandezdarifrancisco@gmail.com
License: MIT
Project-URL: Documentation, https://github.com/DariHernandez/backup_folder_to_zip/blob/master/README.md
Project-URL: Funding, https://www.paypal.com/paypalme/FranciscoDari
Project-URL: Source, https://github.com/DariHernandez/backup_folder_to_zip/
Keywords: zip,backup,back up,auto backup,auto back up
Platform: UNKNOWN
Requires-Python: >=3.7
